stf_client/__init__.py
stf_client/api_client.py
stf_client/configuration.py
stf_client/exceptions.py
stf_client/model_utils.py
stf_client/rest.py
stf_client/api/__init__.py
stf_client/api/admin_api.py
stf_client/api/devices_api.py
stf_client/api/groups_api.py
stf_client/api/user_api.py
stf_client/api/users_api.py
stf_client/apis/__init__.py
stf_client/model/__init__.py
stf_client/model/access_tokens_response.py
stf_client/model/add_adb_public_key_request.py
stf_client/model/add_user_device_payload.py
stf_client/model/conflict.py
stf_client/model/conflict_date.py
stf_client/model/conflict_owner.py
stf_client/model/conflicts_response.py
stf_client/model/device_list_response.py
stf_client/model/device_payload.py
stf_client/model/device_response.py
stf_client/model/devices_payload.py
stf_client/model/error_response.py
stf_client/model/group_list_response.py
stf_client/model/group_payload.py
stf_client/model/group_response.py
stf_client/model/groups_payload.py
stf_client/model/remote_connect_user_device_response.py
stf_client/model/response.py
stf_client/model/token.py
stf_client/model/unexpected_error_response.py
stf_client/model/user_access_token_response.py
stf_client/model/user_access_tokens_response.py
stf_client/model/user_list_response.py
stf_client/model/user_response.py
stf_client/model/users_payload.py
stf_client/models/__init__.py
stf_client-0.1.0.dist-info/METADATA
stf_client-0.1.0.dist-info/WHEEL
stf_client-0.1.0.dist-info/top_level.txt
stf_client-0.1.0.dist-info/RECORD
