Metadata-Version: 2.1
Name: stf-client
Version: 0.1.0
Summary: Smartphone Test Farm client library
Home-page: 
Author: Jussi Vatjus-Anttila
Author-email: jussiva@gmail.com
License: Apache-2.0
Keywords: OpenAPI,OpenAPI-Generator,Smartphone Test Farm,stf,devicefarm,openstf
Requires-Python: >=3.7
Requires-Dist: urllib3 (>=1.25.3)
Requires-Dist: python-dateutil
